bangtal/__init__.py
bangtal/game.py
bangtal/object.py
bangtal/scene.py
bangtal/singleton.py
bangtal/sound.py
bangtal/timer.py
bangtal-0.3.3.dist-info/METADATA
bangtal-0.3.3.dist-info/WHEEL
bangtal-0.3.3.dist-info/top_level.txt
bangtal-0.3.3.dist-info/RECORD
